chemoecology_tools/__init__.py
chemoecology_tools/analysis/__init__.py
chemoecology_tools/analysis/analysis.py
chemoecology_tools/analysis/stats.py
chemoecology_tools/core/__init__.py
chemoecology_tools/core/gcms_experiment.py
chemoecology_tools/py.typed
chemoecology_tools/utils/__init__.py
chemoecology_tools/utils/pubchem_utils.py
chemoecology_tools/visualization/__init__.py
chemoecology_tools/visualization/plotting.py
chemoecology_tools-0.1.0.dist-info/LICENSE
chemoecology_tools-0.1.0.dist-info/METADATA
chemoecology_tools-0.1.0.dist-info/WHEEL
chemoecology_tools-0.1.0.dist-info/entry_points.txt
chemoecology_tools-0.1.0.dist-info/RECORD
