Metadata-Version: 2.1
Name: chemoecology-tools
Version: 0.1.0
Summary: Chemoecology Tools
Home-page: https://github.com/wolfffff/chemoecology-tools
License: MIT
Author: Scott Wolf
Author-email: swwolf@princeton.edu
Requires-Python: >=3.10,<4.0
Classifier: Development Status :: 2 - Pre-Alpha
Classifier: License :: OSI Approved :: MIT License
Classifier: Programming Language :: Python :: 3
Classifier: Programming Language :: Python :: 3.10
Classifier: Programming Language :: Python :: 3.11
Classifier: Programming Language :: Python :: 3.12
Classifier: Programming Language :: Python :: 3.13
Requires-Dist: h5py (>=3.10.0)
Requires-Dist: matplotlib (>=3.8.0)
Requires-Dist: numpy (>=1.24.0)
Requires-Dist: openpyxl (>=3.1.2)
Requires-Dist: pandas (>=2.0.0)
Requires-Dist: pandas-stubs (>=2.2.3.241009,<3.0.0.0)
Requires-Dist: pubchempy (>=1.0.4,<2.0.0)
Requires-Dist: pyyaml (>=6.0.2,<7.0.0)
Requires-Dist: scikit-learn (>=1.3.0)
Requires-Dist: scipy (>=1.11.0)
Requires-Dist: seaborn (>=0.13.0)
Requires-Dist: tqdm (>=4.66.0)
Requires-Dist: types-pyyaml (>=6.0.12.20240917,<7.0.0.0)
Requires-Dist: types-seaborn (>=0.13.2.20241003,<0.14.0.0)
Project-URL: Changelog, https://github.com/wolfffff/chemoecology-tools/releases
Project-URL: Documentation, https://chemoecology-tools.readthedocs.io
Project-URL: Repository, https://github.com/wolfffff/chemoecology-tools
